LICENSE
MANIFEST.in
README.rst
setup.py
weblib/__init__.py
weblib/const.py
weblib/content.py
weblib/control.py
weblib/debug.py
weblib/encoding.py
weblib/error.py
weblib/etree.py
weblib/feed.py
weblib/files.py
weblib/google.py
weblib/html.py
weblib/http.py
weblib/internal.py
weblib/lock.py
weblib/logs.py
weblib/metric.py
weblib/parser.py
weblib/ping.py
weblib/pool.py
weblib/progress.py
weblib/pwork.py
weblib/rex.py
weblib/russian.py
weblib/selenium_tools.py
weblib/structured.py
weblib/system.py
weblib/text.py
weblib/user_agent.py
weblib/w3lib_encoding.py
weblib/watch.py
weblib/work.py
weblib/yandex.py
weblib.egg-info/PKG-INFO
weblib.egg-info/SOURCES.txt
weblib.egg-info/dependency_links.txt
weblib.egg-info/requires.txt
weblib.egg-info/top_level.txt
weblib/export/__init__.py
weblib/export/csv_dumper.py
weblib/export/mysql_dumper.py